ptable/__init__.py
ptable/sheet.py
ptable/table.py
ptable/table_attr.py
ptable/table_merge.py
test/__init__.py
test/run_test.py
test/test_sheet.py
test/test_table.py
test/test_table_merge.py
xlsx_ptable-0.3.5.dist-info/METADATA
xlsx_ptable-0.3.5.dist-info/WHEEL
xlsx_ptable-0.3.5.dist-info/top_level.txt
xlsx_ptable-0.3.5.dist-info/RECORD
