Metadata-Version: 2.1
Name: xlsx-ptable
Version: 0.3.5
Summary: Extract information from log files and create Excel spreadsheets.
Home-page: https://github.com/gupeng1978/tools
Author: Peng Gu
Author-email: gu.peng@intellif.com
License: UNKNOWN
Platform: UNKNOWN
Classifier: Development Status :: 3 - Alpha
Classifier: Intended Audience :: Developers
Classifier: License :: OSI Approved :: MIT License
Classifier: Programming Language :: Python :: 3.6
Classifier: Programming Language :: Python :: 3.7
Classifier: Programming Language :: Python :: 3.8
Classifier: Programming Language :: Python :: 3.9
Requires-Dist: openpyxl (==3.1.2)
Requires-Dist: PyYAML
